Metadata-Version: 1.0
Name: RbxAPI
Version: 0.21.1
Summary: RbxAPI is a Pythonic and efficient Roblox API wrapper. With many quality of life adjustments made during its first iterations, it aims to give you the simplest way of accessing Roblox's API endpoints!
Home-page: UNKNOWN
Author: PythonicIconic
Author-email: coatedalmond@protonmail.com
License: UNKNOWN
Platform: UNKNOWN
